[
  {
    "id": "tr_1783493297808",
    "code": "DA6935-010",
    "product": "프로 파텔라 밴드 3.0",
    "shopNo": "133426976",
    "itemCode": "18072",
    "date": "26/07/08 15:48",
    "size": "S/M",
    "qty": 6,
    "memo": "[물류 ➡️ 부산점] 스마트보충 RT요청"
  },
  {
    "id": "tr_1783493315405",
    "code": "HV8150-102",
    "product": "보메로 플러스",
    "shopNo": "133833694",
    "itemCode": "21395",
    "date": "26/07/08 15:48",
    "size": "250",
    "qty": 2,
    "memo": "[물류 ➡️ 부산점] 스마트보충 RT요청"
  },
  {
    "id": "tr_1783493318197",
    "code": "HV8150-102",
    "product": "보메로 플러스",
    "shopNo": "133833694",
    "itemCode": "21396",
    "date": "26/07/08 15:48",
    "size": "255",
    "qty": 1,
    "memo": "[물류 ➡️ 부산점] 스마트보충 RT요청"
  },
  {
    "id": "tr_1783493320211",
    "code": "HV8150-102",
    "product": "보메로 플러스",
    "shopNo": "133833694",
    "itemCode": "21398",
    "date": "26/07/08 15:48",
    "size": "265",
    "qty": 2,
    "memo": "[물류 ➡️ 부산점] 스마트보충 RT요청"
  },
  {
    "id": "tr_1783493323549",
    "code": "HV8150-102",
    "product": "보메로 플러스",
    "shopNo": "133833694",
    "itemCode": "21399",
    "date": "26/07/08 15:48",
    "size": "270",
    "qty": 2,
    "memo": "[물류 ➡️ 부산점] 스마트보충 RT요청"
  },
  {
    "id": "tr_1783493327788",
    "code": "HV8150-102",
    "product": "보메로 플러스",
    "shopNo": "133833694",
    "itemCode": "21403",
    "date": "26/07/08 15:48",
    "size": "290",
    "qty": 1,
    "memo": "[물류 ➡️ 부산점] 스마트보충 RT요청"
  },
  {
    "id": "tr_1783493328237",
    "code": "HV8150-102",
    "product": "보메로 플러스",
    "shopNo": "133833694",
    "itemCode": "21405",
    "date": "26/07/08 15:48",
    "size": "300",
    "qty": 1,
    "memo": "[물류 ➡️ 부산점] 스마트보충 RT요청"
  },
  {
    "id": "tr_1783493332674",
    "code": "HV8150-102",
    "product": "보메로 플러스",
    "shopNo": "133833694",
    "itemCode": "21401",
    "date": "26/07/08 15:48",
    "size": "280",
    "qty": 1,
    "memo": "[물류 ➡️ 부산점] 스마트보충 RT요청"
  },
  {
    "id": "tr_1783493363926",
    "code": "KD6975",
    "product": "러닝 X 아디제로 클라이마쿨 캡",
    "shopNo": "132706492",
    "itemCode": "27489",
    "date": "26/07/08 15:49",
    "size": "OSFM",
    "qty": 2,
    "memo": "[물류 ➡️ 부산점] 스마트보충 RT요청"
  },
  {
    "id": "tr_1783493370678",
    "code": "HV8154-102",
    "product": "보메로 플러스",
    "shopNo": "133833709",
    "itemCode": "21006",
    "date": "26/07/08 15:49",
    "size": "230",
    "qty": 1,
    "memo": "[물류 ➡️ 부산점] 스마트보충 RT요청"
  },
  {
    "id": "tr_1783493466093",
    "code": "HV8150-003",
    "product": "보메로 플러스",
    "shopNo": "",
    "itemCode": "21419",
    "date": "26/07/08 15:51",
    "size": "265",
    "qty": 2,
    "memo": "[물류 ➡️ 부산점] 스마트보충 RT요청"
  },
  {
    "id": "tr_1783493471462",
    "code": "HV8150-003",
    "product": "보메로 플러스",
    "shopNo": "",
    "itemCode": "21421",
    "date": "26/07/08 15:51",
    "size": "275",
    "qty": 1,
    "memo": "[물류 ➡️ 부산점] 스마트보충 RT요청"
  }
]